{"cameraMode":{"drawMode":0,"name":"Shaded","section":"Shading Mode"},"sceneLighting":true,"audioPlay":false,"sceneViewState":{"m_AlwaysRefresh":false,"showFog":true,"showSkybox":true,"showFlares":true,"showImageEffects":true,"showParticleSystems":true,"showVisualEffectGraphs":true,"m_FxEnabled":true},"in2DMode":false,"pivot":{"x":229.58633422851563,"y":-519.6395263671875,"z":1163.962890625},"rotation":{"x":0.3196740746498108,"y":-0.2917795777320862,"z":0.10416832566261292,"w":0.8954452276229858},"size":423.9979248046875,"orthographic":false}